surgedb/__init__.py
surgedb/surgedb/__init__.py
surgedb/surgedb/libsurgedb_bindings.so
surgedb/surgedb/surgedb.py
surgedb-1.0.0a5.dist-info/METADATA
surgedb-1.0.0a5.dist-info/WHEEL
surgedb-1.0.0a5.dist-info/RECORD
