Metadata-Version: 2.4
Name: surgedb
Version: 1.0.0a5
Summary: A high-performance, lightweight vector database
Keywords: vector-database,similarity-search,hnsw,embedding
Author-email: Meet Sonawane <meet.sonawane2015@gmail.com>
License: MIT
Requires-Python: >=3.7
